[
    {
        "id":"1",
        "CategoryName":"Image Converter",
        "Image_URL":"http://quantumquest.co.in/images/conversion2.jpg"
    },
    {
        "id":"2",
        "CategoryName":"Video Downloader",
        "Image_URL":"http://quantumquest.co.in/images/conversion3.jpg"
    },
    {
        "id":"3",
        "CategoryName":"Document Converter",
        "Image_URL":"http://quantumquest.co.in/images/conversion1.jpg"
    },
    {
        "id":"4",
        "CategoryName":"Audio Converter",
        "Image_URL":"http://quantumquest.co.in/images/conversion4.jpg"
    },
    {
        "id":"5",
        "CategoryName":"Hashtag Generator",
        "Image_URL":"http://quantumquest.co.in/images/conversion5.jpg"
    },
    {
        "id":"6",
        "CategoryName":"File Compression",
        "Image_URL":"http://quantumquest.co.in/images/conversion6.jpg"
    }
]